bfdbhandler/__init__.py
bfdbhandler/dbhandler.py
BFdbhandler-0.0.dist-info/LICENSE
BFdbhandler-0.0.dist-info/METADATA
BFdbhandler-0.0.dist-info/WHEEL
BFdbhandler-0.0.dist-info/top_level.txt
BFdbhandler-0.0.dist-info/RECORD
